verilog/03_full_adder/full_adder.v
module full_adder(
    input wire a,
    input wire b,
    input wire cin,
    output wire sum,
    output wire cout
);

assign sum = a ^ b ^ cin;
assign cout = (a & b) | (b & cin) | (a & cin);





endmodule

verilog/03_full_adder/full_adder_tb.v
`timescale 1ns/1ns

module full_adder_tb;

reg a_in;
reg b_in;
reg cin_in;
wire sum_out;
wire cout_out;

full_adder uut(
    .a(a_in),
    .b(b_in),
    .cin(cin_in),
    .cout(cout_out),
    .sum(sum_out)
);
initial begin
    $dumpfile("full_adder_tb.vcd");
    $dumpvars(0, full_adder_tb);
    a_in = 0; b_in = 0; cin_in = 0; #10; // Test case 1: a=0, b=0, cin=0
    a_in = 0; b_in = 0; cin_in = 1; #10; // Test case 2: a=0, b=0, cin=1
    a_in = 0; b_in = 1; cin_in = 0; #10; // Test case 3: a=0, b=1, cin=0
    a_in = 0; b_in = 1; cin_in = 1; #10; // Test case 4: a=0, b=1, cin=1
    a_in = 1; b_in = 0; cin_in = 0; #10; // Test case 5: a=1, b=0, cin=0
    a_in = 1; b_in = 0; cin_in = 1; #10; // Test case 6: a=1, b=0, cin=1
    a_in = 1; b_in = 1; cin_in = 0; #10; // Test case 7: a=1, b=1, cin=0
    a_in = 1; b_in = 1; cin_in = 1; #10; // Test case 8: a=1, b=1, cin=1
    $finish;

end



endmodule

verilog/03_full_adder/full_adder_tb.vcd
$date
	Thu Jul 02 17:10:43 2026
$end
$version
	Icarus Verilog
$end
$timescale
	1ns
$end
$scope module full_adder_tb $end
$var wire 1 ! sum_out $end
$var wire 1 " cout_out $end
$var reg 1 # a_in $end
$var reg 1 $ b_in $end
$var reg 1 % cin_in $end
$scope module uut $end
$var wire 1 # a $end
$var wire 1 $ b $end
$var wire 1 % cin $end
$var wire 1 " cout $end
$var wire 1 ! sum $end
$upscope $end
$upscope $end
$enddefinitions $end
$comment Show the parameter values. $end
$dumpall
$end
#0
$dumpvars
0%
0$
0#
0"
0!
$end
#10
1!
1%
#20
0%
1$
#30
1"
0!
1%
#40
0"
1!
0%
0$
1#
#50
1"
0!
1%
#60
0%
1$
#70
1!
1%
